gmakepdf/__init__.py
gmakepdf/cli.py
gmakepdf/core.py
gmakepdf-0.1.0.dist-info/licenses/LICENSE
gmakepdf-0.1.0.dist-info/METADATA
gmakepdf-0.1.0.dist-info/WHEEL
gmakepdf-0.1.0.dist-info/top_level.txt
gmakepdf-0.1.0.dist-info/RECORD
