Metadata-Version: 2.4
Name: gmakepdf
Version: 0.1.0
Summary: Fast HTML to PDF conversion using Playwright
Home-page: https://github.com/ganeshkandu/gmakepdf
Author: Ganesh Kandu
Author-email: Ganesh Kandu <kanduganesh@gmail.com>
License-Expression: MIT
Project-URL: Homepage, https://github.com/yourusername/gmakepdf
Keywords: html,pdf,playwright,html-to-pdf
Classifier: Programming Language :: Python :: 3
Classifier: Operating System :: OS Independent
Requires-Python: >=3.9
License-File: LICENSE
Requires-Dist: playwright>=1.40
Dynamic: license-file
